Parsea.py
Parsea-0.0.2.dist-info/LICENSE
Parsea-0.0.2.dist-info/METADATA
Parsea-0.0.2.dist-info/WHEEL
Parsea-0.0.2.dist-info/top_level.txt
Parsea-0.0.2.dist-info/RECORD
