Metadata-Version: 2.1
Name: Parsea
Version: 0.0.2
Summary: Simple Scannerless Parser library for Python
Home-page: https://github.com/Xp-op/Parsea
Author: Xp
Author-email: breakdowneternity@gmail.com
License: UNKNOWN
Project-URL: Bug Tracker, https://github.com/Xp-op/Parsea/issues
Platform: UNKNOWN
Classifier: Programming Language :: Python :: 3
Classifier: License :: OSI Approved :: MIT License
Classifier: Operating System :: OS Independent
Requires-Python: >=3.6
License-File: LICENSE
